contextualise/__init__.py
contextualise/api.py
contextualise/association.py
contextualise/attribute.py
contextualise/file.py
contextualise/image.py
contextualise/link.py
contextualise/map.py
contextualise/note.py
contextualise/settings.py
contextualise/tag.py
contextualise/three_d.py
contextualise/topic.py
contextualise/topic_store.py
contextualise/version.py
contextualise/video.py
contextualise/visualisation.py
contextualise/wsgi.py
contextualise/static/access-denied.svg
contextualise/static/amsify.suggestags.css
contextualise/static/android-chrome-192x192.png
contextualise/static/android-chrome-512x512.png
contextualise/static/app.css
contextualise/static/app.js
contextualise/static/apple-touch-icon.png
contextualise/static/blank-canvas.svg
contextualise/static/browserconfig.xml
contextualise/static/bug-fixing.svg
contextualise/static/contextualise-full-logo.png
contextualise/static/contextualise-full-logo.svg
contextualise/static/contextualise-isometric.png
contextualise/static/contextualise-logo.svg
contextualise/static/default.css
contextualise/static/favicon-16x16.png
contextualise/static/favicon-32x32.png
contextualise/static/favicon.ico
contextualise/static/frontpage.css
contextualise/static/index.css
contextualise/static/index.html
contextualise/static/jquery.amsify.suggestags.js
contextualise/static/mstile-150x150.png
contextualise/static/page-not-found.svg
contextualise/static/security.css
contextualise/static/site.webmanifest
contextualise/static/typeahead.bundle.min.js
contextualise/static/typeahead.css
contextualise/static/void.svg
contextualise/templates/403.html
contextualise/templates/404.html
contextualise/templates/413.html
contextualise/templates/500.html
contextualise/templates/_messages.html
contextualise/templates/index.html
contextualise/templates/layout_1_column.html
contextualise/templates/layout_maps.html
contextualise/templates/layout_notes.html
contextualise/templates/association/create.html
contextualise-1.0.8.dist-info/LICENSE
contextualise-1.0.8.dist-info/METADATA
contextualise-1.0.8.dist-info/WHEEL
contextualise-1.0.8.dist-info/top_level.txt
contextualise-1.0.8.dist-info/RECORD
