Metadata-Version: 2.1
Name: contextualise
Version: 1.0.8
Summary: Contextualise is an effective tool particularly suited for organising information-heavy projects and activities consisting of unstructured and widely diverse data and information resources
Home-page: https://github.com/brettkromkamp/contextualise
Author: Brett Alistair Kromkamp
Author-email: brettkromkamp@gmail.com
Project-URL: Bug Tracker, https://github.com/brettkromkamp/contextualise/issues
Classifier: Development Status :: 4 - Beta
Classifier: Intended Audience :: Science/Research
Classifier: License :: OSI Approved :: MIT License
Classifier: Natural Language :: English
Classifier: Framework :: Flask
Classifier: Operating System :: POSIX :: Linux
Classifier: Programming Language :: Python :: 3
Classifier: Programming Language :: Python :: 3.7
Classifier: Programming Language :: Python :: 3.8
Classifier: Programming Language :: Python :: 3.9
Classifier: Programming Language :: Python :: 3.10
Classifier: Programming Language :: Python :: Implementation :: CPython
Classifier: Topic :: Education
Requires-Python: >=3.7
License-File: LICENSE
Requires-Dist: bcrypt (>=4.0.1)
Requires-Dist: Flask-Mail (>=0.9.1)
Requires-Dist: Flask-SeaSurf (>=1.1.1)
Requires-Dist: Flask-Security-Too (>=5.0.2)
Requires-Dist: Flask-SQLAlchemy (>=3.0.2)
Requires-Dist: Flask (>=2.2.2)
Requires-Dist: gunicorn (>=20.1.0)
Requires-Dist: maya (>=0.6.1)
Requires-Dist: mistune (>=2.0.4)
Requires-Dist: Pygments (>=2.13.0)
Requires-Dist: python-slugify (>=6.1.2)
Requires-Dist: SQLAlchemy (>=1.4.42)
Requires-Dist: topic-db (>=2.0.5)
Requires-Dist: Werkzeug (>=2.2.2)
